{
    "platform": "Instagram",
    "key": "ig_hongjoyful",
    "version":5,
    "name": "hongjoyfu",
    "sub": "직장인 데일리룩 / 출근룩 코디 맛집 ♥︎",
    "openProfileEnabled": true,
    "openProfileText": "SHOP 바로가기",
    "openProfileUrl": "https://hizzi.co.kr/",
    "profileUrl": "https://www.instagram.com/hongjoyful/",
    "avatarUrl": "https://moon6e-max.github.io/shorts-feed/images/allw.png",
    "featured": [
      { "title": "꾸민듯 안꾸민듯 편하지만 예쁜 스타일", "url": "https://www.instagram.com/p/DTnaU9ikSVH/", 
        "thumbUrl": "https://moon6e-max.github.io/shorts-feed/images/all1.jpg" },
      { "title": "언니들💕 가을에는 니트 + 가디건인데욤 !!", "url": "https://www.instagram.com/p/DNXpN5ax-OF/", 
        "thumbUrl": "https://moon6e-max.github.io/shorts-feed/images/all2.jpg" },
      { "title": "언니들💕 제가 드디어 해냈어요!!", "url": "https://www.instagram.com/p/DULmRXRk8zY/", 
        "thumbUrl": "https://moon6e-max.github.io/shorts-feed/images/all3.jpg" },
        { "title": "언니들💕 입는 순간 체형 정리되는 격식룩", "url": "https://www.instagram.com/p/DUE0xDkE4Cm/", 
        "thumbUrl": "https://moon6e-max.github.io/shorts-feed/images/all4.jpg" }
         ]
  }
